<Properties StartupConfiguration="{0C51C955-DC45-93BF-3B9C-A1A4BEA383C6}|">
  <MonoDevelop.Ide.Workbench ActiveDocument="Assets/Scripts/ReversoPlayerPrefs.cs">
    <Files>
      <File FileName="Assets/Scripts/OtherGamesShower.cs" Line="75" Column="13" />
      <File FileName="Assets/GooglePlayGames/ISocialPlatform/PlayGamesPlatform.cs" Line="1132" Column="14" />
      <File FileName="Assets/GooglePlayGames/ISocialPlatform/PlayGamesLocalUser.cs" Line="267" Column="15" />
      <File FileName="Assets/Scripts/SoundManager.cs" Line="40" Column="95" />
      <File FileName="Assets/Scripts/OptionsPanelEvents.cs" Line="58" Column="27" />
      <File FileName="Assets/Scripts/ReversoPlayerPrefs.cs" Line="12" Column="32" />
    </Files>
  </MonoDevelop.Ide.Workbench>
  <MonoDevelop.Ide.DebuggingService.PinnedWatches />
  <MonoDevelop.Ide.Workspace ActiveConfiguration="Debug" />
  <MonoDevelop.Ide.ItemProperties.Assembly-CSharp PreferredExecutionTarget="Unity.Editor" />
  <MonoDevelop.Ide.DebuggingService.Breakpoints>
    <BreakpointStore />
  </MonoDevelop.Ide.DebuggingService.Breakpoints>
  <MultiItemStartupConfigurations />
</Properties>